napier/__init__.py
napier/config.py
napier/napier.py
napier/utilities/__init__.py
napier/utilities/napierbone.py
napier/utilities/napiermath.py
naplock-2.2.2.dist-info/LICENSE
naplock-2.2.2.dist-info/METADATA
naplock-2.2.2.dist-info/WHEEL
naplock-2.2.2.dist-info/top_level.txt
naplock-2.2.2.dist-info/RECORD
