Metadata-Version: 2.1
Name: naplock
Version: 2.2.2
Summary: A cryptographic key pair generator for secure communication.
Author: Akinsunlade Marvelous
Author-email: akinmarvelous2022@gmail.com
License: MIT
License-File: LICENSE
Requires-Dist: numpy
